instabotpy/__init__.py
instabotpy/instabotpy.py
instabotpy-0.0.1.dist-info/LICENSE
instabotpy-0.0.1.dist-info/METADATA
instabotpy-0.0.1.dist-info/WHEEL
instabotpy-0.0.1.dist-info/top_level.txt
instabotpy-0.0.1.dist-info/RECORD
