Metadata-Version: 2.1
Name: instabotpy
Version: 0.0.1
Summary: A small Instagram bot package that uses some basic functions. Download and have fun
Home-page: https://github.com/Krish-ds/Instagram_Bot
Author: Gokula Krishna
Author-email: trgokul99@gmail.com
License: UNKNOWN
Platform: UNKNOWN
Classifier: Programming Language :: Python :: 3
Classifier: License :: OSI Approved :: MIT License
Classifier: Operating System :: OS Independent
Requires-Python: >=3.6
